.travis.yml
CHANGES.rst
LICENSE.txt
README.rst
pytest.ini
setup.py
tox.ini
pyramid_localroles/__init__.py
pyramid_localroles.egg-info/PKG-INFO
pyramid_localroles.egg-info/SOURCES.txt
pyramid_localroles.egg-info/dependency_links.txt
pyramid_localroles.egg-info/requires.txt
pyramid_localroles.egg-info/top_level.txt
pyramid_localroles.egg-info/zip-safe
pyramid_localroles/tests/__init__.py
pyramid_localroles/tests/test_localroles.py