Metadata-Version: 1.0
Name: pyramid-localroles
Version: 0.1
Summary: Local roles authorization policy for Pyramid
Home-page: http://github.com/lrowe/pyramid_localroles
Author: Laurence Rowe
Author-email: laurence@lrowe.co.uk
License: MIT
Platform: UNKNOWN
Classifier: Development Status :: 5 - Production/Stable
Classifier: Environment :: Web Environment
Classifier: Intended Audience :: Developers
Classifier: License :: OSI Approved :: MIT License
Classifier: Operating System :: OS Independent
Classifier: Programming Language :: Python
Classifier: Programming Language :: Python :: 2.7
Classifier: Programming Language :: Python :: 3.3
Classifier: Programming Language :: Python :: 3.4
Classifier: Topic :: Software Development :: Libraries :: Python Modules
